cardlinky/__init__.py
cardlinky/cardlinky.py
cardlinky/types/__init__.py
cardlinky/types/enums/__init__.py
cardlinky/types/enums/account_type.py
cardlinky/types/enums/bill_type.py
cardlinky/types/enums/currency.py
cardlinky/types/enums/enum.py
cardlinky/types/enums/status.py
cardlinky/types/models/__init__.py
cardlinky/types/models/balance.py
cardlinky/types/models/bill.py
cardlinky/types/models/payment.py
cardlinky/types/models/payout.py
cardlinky-1.7.dist-info/LICENSE
cardlinky-1.7.dist-info/METADATA
cardlinky-1.7.dist-info/WHEEL
cardlinky-1.7.dist-info/RECORD
