Metadata-Version: 2.1
Name: cardlinky
Version: 1.7
Summary: Wrapper for the Cardlink API in Python
Home-page: https://github.com/LuK050/cardlinky
License: MIT
Keywords: cardlink,api
Author: LuK050
Author-email: volychevk@gmail.com
Requires-Python: >=3.7,<4.0
Classifier: License :: OSI Approved :: MIT License
Classifier: Programming Language :: Python :: 3
Classifier: Programming Language :: Python :: 3.7
Classifier: Programming Language :: Python :: 3.8
Classifier: Programming Language :: Python :: 3.9
Classifier: Programming Language :: Python :: 3.10
Classifier: Programming Language :: Python :: 3.11
Requires-Dist: pydantic (>=4.5.0,<5.0.0)
Requires-Dist: requests (>=2.28.2,<3.0.0)
Project-URL: Documentation, https://cardlink.link/reference/api
Project-URL: Repository, https://github.com/LuK050/cardlinky
